[
  {
    "placeId": "ChIJ9UCFSPE50i0RVVADcFGCGXI",
    "name": "Desa Kitsuné",
    "address": "",
    "googleMapsUri": "https://maps.google.com/?cid=8221745881024778325",
    "gofoodUrl": ""
  },
  {
    "placeId": "ChIJr9bHQS050i0RW_GuYHY3vaU",
    "name": "Sensorium Bali",
    "address": "",
    "googleMapsUri": "https://maps.google.com/?cid=11942762768424169819",
    "gofoodUrl": ""
  },
  {
    "placeId": "ChIJL3L-Sfc50i0RwlAVew5QCm8",
    "name": "Milk & Madu Beach Road",
    "address": "",
    "googleMapsUri": "https://maps.google.com/?cid=8001295711101866178",
    "gofoodUrl": "https://gofood.co.id/bali/restaurant/milk-madu-beach-road-batu-bolong-9304522a-28f3-457e-92c8-479018bd4018?as=gmaps"
  },
  {
    "placeId": "ChIJ36pywXk40i0Rh9ZZCRMb1fQ",
    "name": "The Avocado Factory",
    "address": "",
    "googleMapsUri": "https://maps.google.com/?cid=17642036883868997255",
    "gofoodUrl": "https://gofood.co.id/bali/restaurant/the-avocado-factory-canggu-e039c2c9-bcfa-4a0f-9bdf-a3c731c40585?as=gmaps"
  },
  {
    "placeId": "ChIJnY-evaw50i0RD_tH6R6pDyw",
    "name": "Revolver Canggu",
    "address": "",
    "googleMapsUri": "https://maps.google.com/?cid=3174942212547410703",
    "gofoodUrl": "https://gofood.co.id/bali/restaurant/revolver-all-day-cafe-canggu-350c909c-273c-4b3e-a305-3f87a6b11ad8?as=gmaps"
  },
  {
    "placeId": "ChIJ1a70wvFH0i0RajIckWuoU14",
    "name": "ZIN Cafe",
    "address": "",
    "googleMapsUri": "https://maps.google.com/?cid=6796961442581721706",
    "gofoodUrl": "https://gofood.co.id/bali/restaurant/zin-cafe-canggu-c3af4ae8-d049-4d3f-be3f-7cdec585073a?as=gmaps"
  },
  {
    "placeId": "ChIJg1ad-75H0i0R8aB_K9oKYj8",
    "name": "Fold Canggu",
    "address": "",
    "googleMapsUri": "https://maps.google.com/?cid=4567224904256037105",
    "gofoodUrl": ""
  },
  {
    "placeId": "ChIJVwZGvMo50i0R5i1fzyT73S4",
    "name": "Sari Kitchen & Community - by Ekosistem",
    "address": "",
    "googleMapsUri": "https://maps.google.com/?cid=3377131431114255846",
    "gofoodUrl": ""
  },
  {
    "placeId": "ChIJq42lSa850i0RziccPzDJXhU",
    "name": "Two Face / Coffee & Brunch [Canggu]",
    "address": "",
    "googleMapsUri": "https://maps.google.com/?cid=1539889331661711310",
    "gofoodUrl": "https://gofood.co.id/bali/restaurant/two-face-coffee-brunch-canggu-a4ed4a2f-7f6a-404a-9949-8aefdc547d1d"
  },
  {
    "placeId": "ChIJSzQz6CQ50i0RalL4caNfcSI",
    "name": "HOME CAFE CANGGU",
    "address": "",
    "googleMapsUri": "https://maps.google.com/?cid=2481870025254261354",
    "gofoodUrl": ""
  },
  {
    "placeId": "ChIJU0lp4SNH0i0R7x72tr13TmY",
    "name": "BAKED. Berawa",
    "address": "",
    "googleMapsUri": "https://maps.google.com/?cid=7371961296754188015",
    "gofoodUrl": "https://gofood.co.id/bali/restaurant/baked-berawa-a4c2db9e-bc6a-47ca-99d1-516ec6f2b659?as=gmaps"
  },
  {
    "placeId": "ChIJZ6Jj8oFH0i0R0sKhEJMIyd8",
    "name": "nüde cafe Berawa",
    "address": "",
    "googleMapsUri": "https://maps.google.com/?cid=16125429368509022930",
    "gofoodUrl": "https://gofood.co.id/bali/restaurant/nude-canggu-pantai-berawa-2f02172f-1e24-4432-8f26-856d5fe66e6e?as=gmaps"
  },
  {
    "placeId": "ChIJcYpksxVH0i0RCDMFafUy5N4",
    "name": "Lusa By/Suka",
    "address": "",
    "googleMapsUri": "https://maps.google.com/?cid=16061018200720356104",
    "gofoodUrl": "https://gofood.co.id/bali/restaurant/lusa-by-suka-berawa-canggu-09f25db4-dfe1-4626-bac8-ac82e8f7def3?as=gmaps"
  },
  {
    "placeId": "ChIJa2bVbaxcBAURDMj_jEzGDqI",
    "name": "Hungry Bird Coffee Roaster",
    "address": "",
    "googleMapsUri": "https://maps.google.com/?cid=11677488915903662092",
    "gofoodUrl": "https://gofood.co.id/bali/restaurant/hungry-bird-coffee-and-roaster-0679c078-d113-468c-9425-159d2a2f639f?as=gmaps"
  },
  {
    "placeId": "ChIJnxFCS3pH0i0RE9mJ0v6ZkHA",
    "name": "Brunch Club Berawa",
    "address": "",
    "googleMapsUri": "https://maps.google.com/?cid=8111152248627255571",
    "gofoodUrl": ""
  },
  {
    "placeId": "ChIJqdO8SytH0i0RkcWicB2oqxQ",
    "name": "Bokashi Berawa",
    "address": "",
    "googleMapsUri": "https://maps.google.com/?cid=1489468946173314449",
    "gofoodUrl": ""
  },
  {
    "placeId": "ChIJOaEQDnk40i0Rzhou4NcRx-w",
    "name": "Crate Cafe",
    "address": "",
    "googleMapsUri": "https://maps.google.com/?cid=17061625332193172174",
    "gofoodUrl": ""
  },
  {
    "placeId": "ChIJD94dpPY50i0R96D3MPX7rrc",
    "name": "ST. ALi - Bali",
    "address": "",
    "googleMapsUri": "https://maps.google.com/?cid=13235793385395560695",
    "gofoodUrl": ""
  },
  {
    "placeId": "ChIJkfDSHYg50i0RBdXQigmMn54",
    "name": "Brunch Club Pererenan",
    "address": "",
    "googleMapsUri": "https://maps.google.com/?cid=11430008351901144325",
    "gofoodUrl": ""
  },
  {
    "placeId": "ChIJYXyNN5U50i0RmIUNsfH9tHw",
    "name": "MIEL SPECIALTY COFFEE CANGGU | CO-WORKING",
    "address": "",
    "googleMapsUri": "https://maps.google.com/?cid=8986086371010381208",
    "gofoodUrl": "https://food.grab.com/id/en/restaurant/online-delivery/6-C2DZUA5DV7CAG2?sourceID=20240418_173706_7338e2208f3839f5_MEXMPS"
  },
  {
    "placeId": "ChIJHzyhoW450i0Rub7_EEvisDY",
    "name": "The Common",
    "address": "",
    "googleMapsUri": "https://maps.google.com/?cid=3940898485984804537",
    "gofoodUrl": "https://gofood.co.id/bali/restaurant/the-common-canggu-23776a6b-6212-4ebc-ba2f-23781152e48f?as=gmaps"
  },
  {
    "placeId": "ChIJMev9G3w40i0RXZlSucHydMw",
    "name": "Cafe Vida Organic",
    "address": "",
    "googleMapsUri": "https://maps.google.com/?cid=14732667194887543133",
    "gofoodUrl": "https://gofood.co.id/bali/restaurant/cafe-vida-pantai-batu-bolong-36f5d6e6-7acf-44e3-8c5b-c4c68977de4a?as=gmaps"
  },
  {
    "placeId": "ChIJg_EuN3s40i0R6kCeRoibycg",
    "name": "Rise & Shine Cafe Canggu",
    "address": "",
    "googleMapsUri": "https://maps.google.com/?cid=14468266287507063018",
    "gofoodUrl": "https://gofood.co.id/bali/restaurant/rise-and-shine-canggu-af3cc4c9-2191-4bf5-ae53-0343a87b42b5?as=gmaps"
  },
  {
    "placeId": "ChIJhz6xqoo50i0RZxslmCS1iow",
    "name": "Blou Cafe Canggu",
    "address": "",
    "googleMapsUri": "https://maps.google.com/?cid=10127105880872000359",
    "gofoodUrl": "https://gofood.co.id/bali/restaurant/blou-cafe-canggu-ecozy-dijiwa-canggu-bali-0f38779f-bdcc-4175-832a-b4e253b0edce?as=gmaps"
  },
  {
    "placeId": "ChIJH21JAz5H0i0R9xl0tIvpu1w",
    "name": "Kawisari Coffee Farm Shop & Eatery Bali",
    "address": "",
    "googleMapsUri": "https://maps.google.com/?cid=6682191258371496439",
    "gofoodUrl": "https://gofood.co.id/bali/restaurant/kawisari-coffee-farm-shop-bali-jl-pantai-batu-bolong-canggu-5d9ddbdf-012c-4394-a34b-d117bb348c0d?as=gmaps"
  },
  {
    "placeId": "ChIJ1_XOtHg40i0R6eyPmtRK6bc",
    "name": "Cafe The Daun",
    "address": "",
    "googleMapsUri": "https://maps.google.com/?cid=13252205655501040873",
    "gofoodUrl": "https://gofood.co.id/bali/restaurant/the-daun-cafe-and-coffee-canggu-ba95f63e-5efc-4707-9a15-81386c67076f?as=gmaps"
  },
  {
    "placeId": "ChIJnT3bt6VH0i0RUgvf_KGh8r8",
    "name": "Zai Cafe Breakfast & Dinner",
    "address": "",
    "googleMapsUri": "https://maps.google.com/?cid=13831295122712496978",
    "gofoodUrl": "https://gofood.co.id/bali/restaurant/zai-cafe-canggu-bali-80351-aba55783-cd2c-4234-96dd-8242cb90797c?as=gmaps"
  },
  {
    "placeId": "ChIJD63X4IU50i0RFkjm_Q5AwGs",
    "name": "Amolas Cafe",
    "address": "",
    "googleMapsUri": "https://maps.google.com/?cid=7764276190720182294",
    "gofoodUrl": "https://gofood.co.id/bali/restaurant/amolas-cafe-canggu-900e5cf5-aa50-4e74-8006-a376bd4ef9b7?as=gmaps"
  },
  {
    "placeId": "ChIJRfVHDQA50i0R78l1hYjP2iM",
    "name": "openhouse cafe",
    "address": "",
    "googleMapsUri": "https://maps.google.com/?cid=2583605521511991791",
    "gofoodUrl": ""
  },
  {
    "placeId": "ChIJzXC1G0A50i0RRtOZNiTSri0",
    "name": "Mimpi Grocery",
    "address": "",
    "googleMapsUri": "https://maps.google.com/?cid=3291799430631117638",
    "gofoodUrl": "https://gofood.co.id/bali/restaurant/mimpi-grocery-kuta-fc20121f-964c-4b73-bb32-f15ab85bfa1c?as=gmaps"
  },
  {
    "placeId": "ChIJB5JLA1c50i0RRPJ0C5V2DnQ",
    "name": "Fine by SATUSATUCOFFEE",
    "address": "",
    "googleMapsUri": "https://maps.google.com/?cid=8362751940588008004",
    "gofoodUrl": ""
  },
  {
    "placeId": "ChIJq_svKGxH0i0RU-zAhMppq8Y",
    "name": "Neighbourhood Food",
    "address": "",
    "googleMapsUri": "https://maps.google.com/?cid=14315652159058799699",
    "gofoodUrl": "https://gofood.co.id/bali/restaurant/neighbourhood-food-bali-berawa-914ddb65-5587-468d-9841-d7b0c5528d47?as=gmaps"
  },
  {
    "placeId": "ChIJQwwZdJ050i0R0ehpWb6QBQc",
    "name": "Barboa Bali",
    "address": "",
    "googleMapsUri": "https://maps.google.com/?cid=505969680367347921",
    "gofoodUrl": "https://gofood.co.id/bali/restaurant/barboa-bali-canggu-padang-82e9d367-91a0-40e9-ba7f-70393b91664f?as=gmaps"
  },
  {
    "placeId": "ChIJt38YXDo50i0RJlB3Oz0PDjg",
    "name": "HOME CAFE MENGWI",
    "address": "",
    "googleMapsUri": "https://maps.google.com/?cid=4039182671463010342",
    "gofoodUrl": ""
  }
]